xian_uwp/.DS_Store
xian_uwp/__init__.py
xian_uwp/client.py
xian_uwp/models.py
xian_uwp/server.py
xian_uwp/server_utils.py
xian_uwp-0.2.4.dist-info/METADATA
xian_uwp-0.2.4.dist-info/WHEEL
xian_uwp-0.2.4.dist-info/RECORD
