Metadata-Version: 2.1
Name: xian-uwp
Version: 0.2.4
Summary: Xian Universal Wallet Protocol - A unified HTTP API interface for Xian wallets and DApps
Author: Endogen
Author-email: endogen@xian.org
Requires-Python: >=3.11,<4.0
Classifier: Programming Language :: Python :: 3
Classifier: Programming Language :: Python :: 3.11
Classifier: Programming Language :: Python :: 3.12
Classifier: Programming Language :: Python :: 3.13
Requires-Dist: fastapi (>=0.116.1,<0.117.0)
Requires-Dist: httpx (>=0.28.1,<0.29.0)
Requires-Dist: pydantic (>=2.11.7,<3.0.0)
Requires-Dist: uvicorn (>=0.35.0,<0.36.0)
Requires-Dist: websockets (>=15.0.1,<16.0.0)
Requires-Dist: xian-py (>=0.4.4,<0.5.0)
